pushka/__init__.py
pushka/base.py
pushka/_http/__init__.py
pushka/_http/aio.py
pushka/_http/base.py
pushka/_http/tornado.py
pushka/_http/utils.py
pushka/_providers/__init__.py
pushka/_providers/parse.py
pushka/_providers/ses.py
pushka/_providers/twilio.py
pushka-0.1.0.dist-info/DESCRIPTION.rst
pushka-0.1.0.dist-info/METADATA
pushka-0.1.0.dist-info/RECORD
pushka-0.1.0.dist-info/WHEEL
pushka-0.1.0.dist-info/metadata.json
pushka-0.1.0.dist-info/top_level.txt
