Metadata-Version: 2.0
Name: pushka
Version: 0.1.0
Summary: Push notifications, SMS, and emails on top of asyncio
